{
  "title": "Episode #115 - ",
  "blurb": "Roy van de Water, Clayton Lengel-Zigich, Derek Neighbors and Jade Meskill discuss an article that was published on <a href=\"http://agileweekly.com\">Agile Weekly</a> this week: <a href=\"http://agile.dzone.com/articles/commitment-considered-harmful?utm_source=feedburner&utm_medium=feed&utm_campaign=Feed%3A+zones%2Fagile+%28Agile+Zone%29\">Commitment Considered Harmful</a>",
  "episode_number": "115",
  "guest_twitter": "",
  "publish_date": {
    "year":   "2013",
    "month":  "07",
    "day":    "25",
    "hour":   "06",
    "minute": "00"
  },
  "tags": [
    "Roy van de Water",
    "Clayton Lengel-Zigich",
    "Derek Neighbors",
    "Jade Meskill"
  ]
}
